FFinfo/Module.py
FFinfo/__init__.py
FFinfo-1.0.9.dist-info/METADATA
FFinfo-1.0.9.dist-info/WHEEL
FFinfo-1.0.9.dist-info/top_level.txt
FFinfo-1.0.9.dist-info/RECORD
