Metadata-Version: 2.1
Name: FFinfo
Version: 1.0.9
Requires-Dist: requests
Requires-Dist: python-dotenv
